videoio/__init__.py
videoio/info.py
videoio/video_rgb.py
videoio/video_uint16.py
videoio-0.3.0.dist-info/LICENSE
videoio-0.3.0.dist-info/METADATA
videoio-0.3.0.dist-info/WHEEL
videoio-0.3.0.dist-info/top_level.txt
videoio-0.3.0.dist-info/RECORD
