Metadata-Version: 2.1
Name: videoio
Version: 0.3.0
Summary: Module for saving and loading images and depth as H.264 video
Home-page: https://github.com/vguzov/videoio
Author: Vladimir Guzov
Author-email: guzov.mail@gmail.com
Keywords: mp4,png,h264,video,image,depth,ffmpeg
Classifier: Intended Audience :: Developers
Classifier: License :: OSI Approved :: Apache Software License
Classifier: Natural Language :: English
Classifier: Operating System :: OS Independent
Classifier: Programming Language :: Python
Classifier: Programming Language :: Python :: 3
License-File: LICENSE
Requires-Dist: numpy
Requires-Dist: ffmpeg-python
